hillcipher/__init__.py
hillcipher/cipher.py
hillcipher/utils.py
tests/__init__.py
tests/test_cipher.py
hill_cipher_for_educational_use-0.1.0.dist-info/LICENSE
hill_cipher_for_educational_use-0.1.0.dist-info/METADATA
hill_cipher_for_educational_use-0.1.0.dist-info/WHEEL
hill_cipher_for_educational_use-0.1.0.dist-info/top_level.txt
hill_cipher_for_educational_use-0.1.0.dist-info/RECORD
