Metadata-Version: 2.1
Name: hill-cipher-for-educational-use
Version: 0.1.0
Summary: A Python library for the classical Hill Cipher encryption algorithm.
Home-page: https://github.com/wataru-sakamoto/hill-cipher
Author: Wataru Sakamoto
Author-email: Wataru Sakamoto <heisei123abc@gmail.com>
License: MIT License
Project-URL: Homepage, https://github.com/wataru-sakamoto/hill-cipher
Project-URL: Documentation, https://github.com/wataru-sakamoto/hill-cipher#readme
Project-URL: Source, https://github.com/wataru-sakamoto/hill-cipher
Project-URL: BugTracker, https://github.com/wataru-sakamoto/hill-cipher/issues
Keywords: hill cipher,cryptography,encryption,python
Classifier: Programming Language :: Python :: 3
Classifier: License :: OSI Approved :: MIT License
Classifier: Operating System :: OS Independent
Classifier: Topic :: Security :: Cryptography
Requires-Python: >=3.7
License-File: LICENSE
Requires-Dist: numpy>=1.20
